[
  {
    "id": 13,
    "weather": "cloudy",
    "date": 1456566101,
    "imgUrl": "./images/photos/cloudy11.jpg",
    "latitude": 33.3616666,
    "longitude": 126.5269779,
    "location": {
      "province": "제주특별자치도",
      "city": "제주시",
      "town": "오등동",
      "fullAddress": "제주특별자치도 제주시 오등동 한라산"
    },
    "description": "지나가다 보이는 강아지와 한 컷!"
  },
  {
    "id": 17,
    "weather": "rainy",
    "date": 1489319121,
    "imgUrl": "./images/photos/rain2.jpg",
    "latitude": 35.1586975,
    "longitude": 129.1581955,
    "location": {
      "province": "부산광역시",
      "city": "해운대구",
      "town": "중동",
      "fullAddress": "부산광역시 해운대구 중동 해운대해수욕장"
    },
    "description": "오 ㅋㅋ 부산해운대 도착하니까 비 그침"
  },
  {
    "id": 18,
    "weather": "rainy",
    "date": 1489320611,
    "imgUrl": "./images/photos/rain8.jpg",
    "latitude": 35.1586975,
    "longitude": 129.1581955,
    "location": {
      "province": "부산광역시",
      "city": "해운대구",
      "town": "중동",
      "fullAddress": "부산광역시 해운대구 중동 해운대해수욕장"
    },
    "description": "해수욕장 근처에 밥 먹으러 왔는데 다시 비오네 ㅠㅠ 와.. 근데 부산 진짜 좋다"
  },
  {
    "id": 22,
    "weather": "rainy",
    "date": 1491036732,
    "imgUrl": "./images/photos/rain9.jpg",
    "latitude": 37.366139,
    "longitude": 127.1402713,
    "location": {
      "province": "경기도",
      "city": "성남시",
      "town": "분당구",
      "fullAddress": "경기도 성남시 분당구 분당동 새롬교회"
    },
    "description": "준비 다하고 밖에 나왔는데 비가 조금씩 내리네 시무룩"
  },
  {
    "id": 23,
    "weather": "rainy",
    "date": 1491044631,
    "imgUrl": "./images/photos/rain4.jpg",
    "latitude": 37.433886,
    "longitude": 127.0792743,
    "location": {
      "province": "경기도",
      "city": "성남시",
      "town": "수정구",
      "fullAddress": "경기도 성남시 수정구 신구대학교식물원"
    },
    "description": "신구대학교식물원 입구! 길가에도 카페에도 사람이 엄청많네 ㅎㅎ"
  },
  {
    "id":200,
    "weather":"sunny",
    "date":1476961749,
    "imgUrl": "./images/photos/sunny_200.jpg",
    "latitude": 37.5305156,
    "longitude": 126.9459477,
    "location": {
      "province": "서울시",
      "city": "용산구",
      "town": "원효로",
      "fullAddress": "서울시 용산구 원효로 우리집"
    },
    "description": "우리집 시바 산책시키던날... 흘겨보는게 맘에안든다 시바놈... 시바는 기분이 좋은가보다 벌써부터 주인말을 듣지않기 시작한다 시바녀석... "
  },
  {
    "id":201,
    "weather":"sunny",
    "date":1476961749,
    "imgUrl": "./images/photos/sunny_201.jpg",
    "latitude": 37.5305156,
    "longitude": 126.9459477,
    "location": {
      "province": "서울시",
      "city": "용산구",
      "town": "원효로",
      "fullAddress": "서울시 용산구 원효로 우리집"
    },
    "description": "내 최애팀 토트넘 컬렉션 완성...ㅠㅠ 직구하는데 30일이나걸렸는데 기다린 보람이 있다.. 넘나 영롱한것.... 다음은 리버풀꺼 사서 모아야징"
  },
  {
    "id":202,
    "weather":"sunny",
    "date": 1471691349,
    "imgUrl": "./images/photos/sunny_202.jpg",
    "latitude": 37.5305156,
    "longitude": 126.9459477,
    "location": {
      "province": "서울시",
      "city": "용산구",
      "town": "원효로",
      "fullAddress": "서울시 용산구 원효로 우리집"
    },
    "description": "오늘 손흥민이 멀티골넣었다. 내가 다 눈물이났다.. 알리가 어시스트해줬는데 별로 맘에안들긴 한데 요새 패스 많이해주니까 응원해준다."
  },
  {
    "id":203,
    "weather":"rainy",
    "date": 1471691349,
    "imgUrl": "./images/photos/rainy_200.jpg",
    "latitude": 37.4968281,
    "longitude": 126.9978992,
    "location": {
      "province": "서울시",
      "city": "강남구",
      "town": "신사동",
      "fullAddress": "서울시 강남구 신사동 퇴근길"
    },
    "description": "비가 넘나많이온다.. 퇴근직전에 한두방울 오더니만 결국 엄청많이왔다... 기가막히게 내가 새차만 하면 꼭 비가온다. 우라질 여름날씨...에휴"
  },
  {
    "id":204,
    "weather":"rainy",
    "date": 1471691349,
    "imgUrl": "./images/photos/rainy_201.jpg",
    "latitude": 37.4968281,
    "longitude": 126.9978992,
    "location": {
      "province": "서울시",
      "city": "강남구",
      "town": "신사동",
      "fullAddress": "서울시 강남구 신사동 퇴근길"
    },
    "description": "비가 넘나많이온다.. 퇴근직전에 한두방울 오더니만 결국 엄청많이왔다... 기가막히게 내가 새차만 하면 꼭 비가온다. 우라질 여름날씨...에휴"
  },
  {
    "id":205,
    "weather":"cloudy",
    "date": 1471691349,
    "imgUrl": "./images/photos/cloudy_200.jpg",
    "latitude": 37.4763539,
    "longitude": 126.6160047,
    "location": {
      "province": "인천광역시",
      "city": "중구",
      "town": "북성동",
      "fullAddress": "인천광역시 중구 북성동 차이나타운"
    },
    "description": "여자친구랑 차이나타운 여행!! 진짜 중국처럼 보이게 사진찍은거같다. 비가오다가 말다가 해서 아예 우산쓰고찍어버렸다... 날씨빼고는 너무 좋았던 여행~"
  },
  {
    "id":206,
    "weather":"cloudy",
    "date": 1471691349,
    "imgUrl": "./images/photos/cloudy_201.jpg",
    "latitude": 37.4763539,
    "longitude": 126.6160047,
    "location": {
      "province": "인천광역시",
      "city": "중구",
      "town": "북성동",
      "fullAddress": "인천광역시 중구 북성동 차이나타운"
    },
    "description": "여자친구랑 차이나타운 여행!! 진짜 중국처럼 보이게 사진찍은거같다. 비가오다가 말다가 해서 아예 우산쓰고찍어버렸다... 날씨빼고는 너무 좋았던 여행~"
  },
  {
    "id":207,
    "weather":"cloudy",
    "date": 1471691349,
    "imgUrl": "./images/photos/cloudy_202.jpg",
    "latitude": 37.5305156,
    "longitude": 126.9459477,
    "location": {
      "province": "서울시",
      "city": "용산구",
      "town": "원효로",
      "fullAddress": "서울시 용산구 원효로 용산아이파크몰 풋살장"
    },
    "description": "여자친구랑 차이나타운 여행갔다가 집에가는길에 친구랑 용산에서 풋살한경기 하고 집가려고 왔다. 쉬는중에 한컷 ~ 오늘 거의 호날두빙의했음."
  },
  {
    "id":208,
    "weather":"snowy",
    "date": 1482232149,
    "imgUrl": "./images/photos/snowy_200.jpg",
    "latitude": 37.5305156,
    "longitude": 126.9459477,
    "location": {
      "province": "서울시",
      "city": "용산구",
      "town": "원효로",
      "fullAddress": "서울시 용산구 한강로 용산역"
    },
    "description": "용산에서 출발전에 한컷~ 눈이 엄처와서 플랫폼이 다덮였다...전주가는데 너무 기대된다. 타자마자 바로 꿀잠 개꿀~"
  },
  {
    "id":209,
    "weather":"snowy",
    "date": 1482232149,
    "imgUrl": "./images/photos/snowy_201.jpg",
    "latitude": 35.84977,
    "longitude": 127.1596093,
    "location": {
      "province": "전주시",
      "city": "우아1동",
      "town": "동부대로",
      "fullAddress": "전주시 우아1동 동부대로 전주역"
    },
    "description": "드디어 전주역 도착!! 동네친구들 만나러 가는길에 차막혀서 중간에 한컷 ~ 항상 오지만 전주는 너무 오래걸린다. 눈와서 더 오래걸린거같네.."
  },
  {
    "id":210,
    "weather":"snowy",
    "date": 1482232149,
    "imgUrl": "./images/photos/snowy_202.jpg",
    "latitude": 35.84977,
    "longitude": 127.1596093,
    "location": {
      "province": "전주시",
      "city": "우아1동",
      "town": "동부대로",
      "fullAddress": "전주시 우아1동 동부대로 전주역"
    },
    "description": "드디어 전주역 도착!! 동네친구들 만나러 가는길에 차막혀서 중간에 한컷 ~ 항상 오지만 전주는 너무 오래걸린다. 눈와서 더 오래걸린거같네.."
  },
  {
    "id":211,
    "weather":"snowy",
    "date": 1482232149,
    "imgUrl": "./images/photos/snowy_203.jpg",
    "latitude": 35.84977,
    "longitude": 127.1596093,
    "location": {
      "province": "전주시",
      "city": "우아1동",
      "town": "동부대로",
      "fullAddress": "전주시 우아1동 동부대로 전주역"
    },
    "description": "드디어 전주역 도착!! 동네친구들 만나러 가는길에 차막혀서 중간에 한컷 ~ 항상 오지만 전주는 너무 오래걸린다. 눈와서 더 오래걸린거같네.."
  },
  {
    "id":212,
    "weather":"snowy",
    "date": 1482232149,
    "imgUrl": "./images/photos/snowy_204.jpg",
    "latitude": 35.84977,
    "longitude": 127.1596093,
    "location": {
      "province": "전주시",
      "city": "우아1동",
      "town": "동부대로",
      "fullAddress": "전주시 우아1동 동부대로 전주역"
    },
    "description": "드디어 전주역 도착!! 동네친구들 만나러 가는길에 차막혀서 중간에 한컷 ~ 항상 오지만 전주는 너무 오래걸린다. 눈와서 더 오래걸린거같네.."
  },
  {
    "id":213,
    "weather":"snowy",
    "date": 1482232149,
    "imgUrl": "./images/photos/snowy_205.jpg",
    "latitude": 35.84977,
    "longitude": 127.1596093,
    "location": {
      "province": "전주시",
      "city": "우아1동",
      "town": "동부대로",
      "fullAddress": "전주시 우아1동 동부대로 전주역"
    },
    "description": "드디어 전주역 도착!! 동네친구들 만나러 가는길에 차막혀서 중간에 한컷 ~ 항상 오지만 전주는 너무 오래걸린다. 눈와서 더 오래걸린거같네.."
  },
  {
    "id":214,
    "weather":"snowy",
    "date": 1482232149,
    "imgUrl": "./images/photos/snowy_206.jpg",
    "latitude": 35.84977,
    "longitude": 127.1596093,
    "location": {
      "province": "전주시",
      "city": "우아1동",
      "town": "동부대로",
      "fullAddress": "전주시 우아1동 동부대로 전주역"
    },
    "description": "드디어 집에 도착~ 우리집 냥이랑 강아지가 못본사이 너무많이컷다ㅜㅜ 겨울이라 산책도 못시켜주고 미안한데 자주 와야겠다~ 여전히 고양이는 시크하게 쳐다도안보네"
  },
  {
    "id":215,
    "weather":"snowy",
    "date": 1482232149,
    "imgUrl": "./images/photos/snowy_207.jpg",
    "latitude": 35.84977,
    "longitude": 127.1596093,
    "location": {
      "province": "전주시",
      "city": "우아1동",
      "town": "동부대로",
      "fullAddress": "전주시 우아1동 동부대로 전주역"
    },
    "description": "드디어 집에 도착~ 우리집 냥이랑 강아지가 못본사이 너무많이컷다ㅜㅜ 겨울이라 산책도 못시켜주고 미안한데 자주 와야겠다~ 여전히 고양이는 시크하게 쳐다도안보네"
  },
  {
    "id":216,
    "weather":"snowy",
    "date": 1482232149,
    "imgUrl": "./images/photos/snowy_208.jpg",
    "latitude": 35.84977,
    "longitude": 127.1596093,
    "location": {
      "province": "전주시",
      "city": "우아1동",
      "town": "동부대로",
      "fullAddress": "전주시 우아1동 동부대로 전주역"
    },
    "description": "동생도 기숙사 있다가 집에왔다. 눈오는데 기분이 좋은지 나가서 설정샷 찍어달라고 난리다. 이한장을 위해 몇십장을 찍었는지... 저녁엔 치킨이나 사달라해야지"
  },
  {
    "id":217,
    "weather":"snowy",
    "date": 1482232149,
    "imgUrl": "./images/photos/snowy_209.jpg",
    "latitude": 35.84977,
    "longitude": 127.1596093,
    "location": {
      "province": "전주시",
      "city": "우아1동",
      "town": "동부대로",
      "fullAddress": "전주시 우아1동 동부대로 전주역"
    },
    "description": "동생도 기숙사 있다가 집에왔다. 눈오는데 기분이 좋은지 나가서 설정샷 찍어달라고 난리다. 이한장을 위해 몇십장을 찍었는지... 저녁엔 치킨이나 사달라해야지"
  },
  {
    "id":218,
    "weather":"snowy",
    "date": 1482232149,
    "imgUrl": "./images/photos/snowy_210.jpg",
    "latitude": 35.84977,
    "longitude": 127.1596093,
    "location": {
      "province": "전주시",
      "city": "우아1동",
      "town": "동부대로",
      "fullAddress": "전주시 우아1동 동부대로 전주역"
    },
    "description": "엄마아빠라 밖에 나왔다. 눈오는데 기분이 좋으신지 나가서 설정샷 찍어달라고 하셔서 찍어봤다. 이한장을 위해 몇십장을 찍었는지... 저녁엔 치킨이나 사달라해야지"
  },
  {
    "id": 101,
    "weather": "sunny",
    "date": 1498230000,
    "imgUrl": "./images/photos/sunny101.jpg",
    "latitude": 37.8892953,
    "longitude": 127.7716569,
    "location": {
      "province": "강원도",
      "city": "춘천",
      "town": "동면",
      "fullAddress": "강원도 춘천 동면 네이버데이터센터각"
    },
    "description": "네이버 데이터센터 각에 왔다 음식도 맛있고 공기도 좋고 풋살장도 있고 농구장도 있고 배드민턴 장도 있고 없는게 없는 것 같다. 우리 회사도 이쪽으로 이사왔으면 좋겠다 열심히 해서 우승 해야겠다"
  },
  {
    "id": 102,
    "weather": "sunny",
    "date": 1498230060,
    "imgUrl": "./images/photos/sunny102.jpg",
    "latitude": 37.8892953,
    "longitude": 127.7716569,
    "location": {
      "province": "강원도",
      "city": "춘천",
      "town": "동면",
      "fullAddress": "강원도 춘천 동면 네이버데이터센터각"
    },
    "description": "네이버 데이터센터 각에 왔다 음식도 맛있고 공기도 좋고 풋살장도 있고 농구장도 있고 배드민턴 장도 있고 없는게 없는 것 같다. 우리 회사도 이쪽으로 이사왔으면 좋겠다 열심히 해서 우승 해야겠다"
  },
  {
    "id": 103,
    "weather": "sunny",
    "date": 1498230120,
    "imgUrl": "./images/photos/sunny103.jpg",
    "latitude": 37.8892953,
    "longitude": 127.7716569,
    "location": {
      "province": "강원도",
      "city": "춘천",
      "town": "동면",
      "fullAddress": "강원도 춘천 동면 네이버데이터센터각"
    },
    "description": "네이버 데이터센터 각에 왔다 음식도 맛있고 공기도 좋고 풋살장도 있고 농구장도 있고 배드민턴 장도 있고 없는게 없는 것 같다. 우리 회사도 이쪽으로 이사왔으면 좋겠다 열심히 해서 우승 해야겠다"
  },
  {
    "id": 104,
    "weather": "sunny",
    "date": 1498230180,
    "imgUrl": "./images/photos/sunny104.jpg",
    "latitude": 37.8892953,
    "longitude": 127.7716569,
    "location": {
      "province": "강원도",
      "city": "춘천",
      "town": "동면",
      "fullAddress": "강원도 춘천 동면 네이버데이터센터각"
    },
    "description": "네이버 데이터센터 각에 왔다 음식도 맛있고 공기도 좋고 풋살장도 있고 농구장도 있고 배드민턴 장도 있고 없는게 없는 것 같다. 우리 회사도 이쪽으로 이사왔으면 좋겠다 열심히 해서 우승 해야겠다"
  },
  {
    "id": 105,
    "weather": "sunny",
    "date": 1498230240,
    "imgUrl": "./images/photos/sunny105.jpg",
    "latitude": 37.8892953,
    "longitude": 127.7716569,
    "location": {
      "province": "강원도",
      "city": "춘천",
      "town": "동면",
      "fullAddress": "강원도 춘천 동면 네이버데이터센터각"
    },
    "description": "네이버 데이터센터 각에 왔다 음식도 맛있고 공기도 좋고 풋살장도 있고 농구장도 있고 배드민턴 장도 있고 없는게 없는 것 같다. 우리 회사도 이쪽으로 이사왔으면 좋겠다 열심히 해서 우승 해야겠다"
  },
  {
    "id": 106,
    "weather": "sunny",
    "date": 1498230300,
    "imgUrl": "./images/photos/sunny106.jpg",
    "latitude": 37.8892953,
    "longitude": 127.7716569,
    "location": {
      "province": "강원도",
      "city": "춘천",
      "town": "동면",
      "fullAddress": "강원도 춘천 동면 네이버데이터센터각"
    },
    "description": "네이버 데이터센터 각에 왔다 음식도 맛있고 공기도 좋고 풋살장도 있고 농구장도 있고 배드민턴 장도 있고 없는게 없는 것 같다. 우리 회사도 이쪽으로 이사왔으면 좋겠다 열심히 해서 우승 해야겠다"
  },
  {
    "id": 107,
    "weather": "sunny",
    "date": 1498230360,
    "imgUrl": "./images/photos/sunny107.jpg",
    "latitude": 37.8892953,
    "longitude": 127.7716569,
    "location": {
      "province": "강원도",
      "city": "춘천",
      "town": "동면",
      "fullAddress": "강원도 춘천 동면 네이버데이터센터각"
    },
    "description": "네이버 데이터센터 각에 왔다 음식도 맛있고 공기도 좋고 풋살장도 있고 농구장도 있고 배드민턴 장도 있고 없는게 없는 것 같다. 우리 회사도 이쪽으로 이사왔으면 좋겠다 열심히 해서 우승 해야겠다"
  },
  {
    "id": 108,
    "weather": "sunny",
    "date": 1498230420,
    "imgUrl": "./images/photos/sunny108.jpg",
    "latitude": 37.8892953,
    "longitude": 127.7716569,
    "location": {
      "province": "강원도",
      "city": "춘천",
      "town": "동면",
      "fullAddress": "강원도 춘천 동면 네이버데이터센터각"
    },
    "description": "네이버 데이터센터 각에 왔다 음식도 맛있고 공기도 좋고 풋살장도 있고 농구장도 있고 배드민턴 장도 있고 없는게 없는 것 같다. 우리 회사도 이쪽으로 이사왔으면 좋겠다 열심히 해서 우승 해야겠다"
  },
  {
    "id": 109,
    "weather": "sunny",
    "date": 1498230480,
    "imgUrl": "./images/photos/sunny109.jpg",
    "latitude": 37.8892953,
    "longitude": 127.7716569,
    "location": {
      "province": "강원도",
      "city": "춘천",
      "town": "동면",
      "fullAddress": "강원도 춘천 동면 네이버데이터센터각"
    },
    "description": "네이버 데이터센터 각에 왔다 음식도 맛있고 공기도 좋고 풋살장도 있고 농구장도 있고 배드민턴 장도 있고 없는게 없는 것 같다. 우리 회사도 이쪽으로 이사왔으면 좋겠다 열심히 해서 우승 해야겠다"
  },
  {
    "id": 110,
    "weather": "sunny",
    "date": 1498230650,
    "imgUrl": "./images/photos/sunny110.jpg",
    "latitude": 37.8892953,
    "longitude": 127.7716569,
    "location": {
      "province": "강원도",
      "city": "춘천",
      "town": "동면",
      "fullAddress": "강원도 춘천 동면 네이버데이터센터각"
    },
    "description": "네이버 데이터센터 각에 왔다 음식도 맛있고 공기도 좋고 풋살장도 있고 농구장도 있고 배드민턴 장도 있고 없는게 없는 것 같다. 우리 회사도 이쪽으로 이사왔으면 좋겠다 열심히 해서 우승 해야겠다"
  },
  {
    "id": 111,
    "weather": "sunny",
    "date": 1498230800,
    "imgUrl": "./images/photos/sunny111.jpg",
    "latitude": 37.8892953,
    "longitude": 127.7716569,
    "location": {
      "province": "강원도",
      "city": "춘천",
      "town": "동면",
      "fullAddress": "강원도 춘천 동면 네이버데이터센터각"
    },
    "description": "네이버 데이터센터 각에 왔다 음식도 맛있고 공기도 좋고 풋살장도 있고 농구장도 있고 배드민턴 장도 있고 없는게 없는 것 같다. 우리 회사도 이쪽으로 이사왔으면 좋겠다 열심히 해서 우승 해야겠다"
  },
  {
    "id": 112,
    "weather": "sunny",
    "date": 1498230500,
    "imgUrl": "./images/photos/sunny112.jpg",
    "latitude": 37.8892953,
    "longitude": 127.7716569,
    "location": {
      "province": "강원도",
      "city": "춘천",
      "town": "동면",
      "fullAddress": "강원도 춘천 동면 네이버데이터센터각"
    },
    "description": "네이버 데이터센터 각에 왔다 음식도 맛있고 공기도 좋고 풋살장도 있고 농구장도 있고 배드민턴 장도 있고 없는게 없는 것 같다. 우리 회사도 이쪽으로 이사왔으면 좋겠다 열심히 해서 우승 해야겠다"
  },
  {
    "id": 113,
    "weather": "sunny",
    "date": 1498230580,
    "imgUrl": "./images/photos/sunny113.jpg",
    "latitude": 37.8892953,
    "longitude": 127.7716569,
    "location": {
      "province": "강원도",
      "city": "춘천",
      "town": "동면",
      "fullAddress": "강원도 춘천 동면 네이버데이터센터각"
    },
    "description": "네이버 데이터센터 각에 왔다 음식도 맛있고 공기도 좋고 풋살장도 있고 농구장도 있고 배드민턴 장도 있고 없는게 없는 것 같다. 우리 회사도 이쪽으로 이사왔으면 좋겠다 열심히 해서 우승 해야겠다"
  },
  {
    "id": 114,
    "weather": "sunny",
    "date": 1498230690,
    "imgUrl": "./images/photos/sunny114.jpg",
    "latitude": 37.8892953,
    "longitude": 127.7716569,
    "location": {
      "province": "강원도",
      "city": "춘천",
      "town": "동면",
      "fullAddress": "강원도 춘천 동면 네이버데이터센터각"
    },
    "description": "네이버 데이터센터 각에 왔다 음식도 맛있고 공기도 좋고 풋살장도 있고 농구장도 있고 배드민턴 장도 있고 없는게 없는 것 같다. 우리 회사도 이쪽으로 이사왔으면 좋겠다 열심히 해서 우승 해야겠다"
  },
  {
    "id": 115,
    "weather": "sunny",
    "date": 1498230820,
    "imgUrl": "./images/photos/sunny115.jpg",
    "latitude": 37.8892953,
    "longitude": 127.7716569,
    "location": {
      "province": "강원도",
      "city": "춘천",
      "town": "동면",
      "fullAddress": "강원도 춘천 동면 네이버데이터센터각"
    },
    "description": "네이버 데이터센터 각에 왔다 음식도 맛있고 공기도 좋고 풋살장도 있고 농구장도 있고 배드민턴 장도 있고 없는게 없는 것 같다. 우리 회사도 이쪽으로 이사왔으면 좋겠다 열심히 해서 우승 해야겠다"
  },
  {
    "id": 116,
    "weather": "sunny",
    "date": 1498230920,
    "imgUrl": "./images/photos/sunny116.jpg",
    "latitude": 37.8892953,
    "longitude": 127.7716569,
    "location": {
      "province": "강원도",
      "city": "춘천",
      "town": "동면",
      "fullAddress": "강원도 춘천 동면 네이버데이터센터각"
    },
    "description": "네이버 데이터센터 각에 왔다 음식도 맛있고 공기도 좋고 풋살장도 있고 농구장도 있고 배드민턴 장도 있고 없는게 없는 것 같다. 우리 회사도 이쪽으로 이사왔으면 좋겠다 열심히 해서 우승 해야겠다"
  },
  {
    "id": 117,
    "weather": "sunny",
    "date": 1498231020,
    "imgUrl": "./images/photos/sunny117.jpg",
    "latitude": 37.8892953,
    "longitude": 127.7716569,
    "location": {
      "province": "강원도",
      "city": "춘천",
      "town": "동면",
      "fullAddress": "강원도 춘천 동면 네이버데이터센터각"
    },
    "description": "네이버 데이터센터 각에 왔다 음식도 맛있고 공기도 좋고 풋살장도 있고 농구장도 있고 배드민턴 장도 있고 없는게 없는 것 같다. 우리 회사도 이쪽으로 이사왔으면 좋겠다 열심히 해서 우승 해야겠다"
  },
  {
    "id": 118,
    "weather": "sunny",
    "date": 1498231100,
    "imgUrl": "./images/photos/sunny118.jpg",
    "latitude": 37.8892953,
    "longitude": 127.7716569,
    "location": {
      "province": "강원도",
      "city": "춘천",
      "town": "동면",
      "fullAddress": "강원도 춘천 동면 네이버데이터센터각"
    },
    "description": "네이버 데이터센터 각에 왔다 음식도 맛있고 공기도 좋고 풋살장도 있고 농구장도 있고 배드민턴 장도 있고 없는게 없는 것 같다. 우리 회사도 이쪽으로 이사왔으면 좋겠다 열심히 해서 우승 해야겠다"
  },
  {
    "id": 119,
    "weather": "sunny",
    "date": 1498231230,
    "imgUrl": "./images/photos/sunny119.jpg",
    "latitude": 37.8892953,
    "longitude": 127.7716569,
    "location": {
      "province": "강원도",
      "city": "춘천",
      "town": "동면",
      "fullAddress": "강원도 춘천 동면 네이버데이터센터각"
    },
    "description": "네이버 데이터센터 각에 왔다 음식도 맛있고 공기도 좋고 풋살장도 있고 농구장도 있고 배드민턴 장도 있고 없는게 없는 것 같다. 우리 회사도 이쪽으로 이사왔으면 좋겠다 열심히 해서 우승 해야겠다"
  },
  {
    "id": 120,
    "weather": "sunny",
    "date": 1498231480,
    "imgUrl": "./images/photos/sunny120.jpg",
    "latitude": 37.8892953,
    "longitude": 127.7716569,
    "location": {
      "province": "강원도",
      "city": "춘천",
      "town": "동면",
      "fullAddress": "강원도 춘천 동면 네이버데이터센터각"
    },
    "description": "네이버 데이터센터 각에 왔다 음식도 맛있고 공기도 좋고 풋살장도 있고 농구장도 있고 배드민턴 장도 있고 없는게 없는 것 같다. 우리 회사도 이쪽으로 이사왔으면 좋겠다 열심히 해서 우승 해야겠다"
  },
  {
    "id": 121,
    "weather": "sunny",
    "date": 1498231600,
    "imgUrl": "./images/photos/sunny121.jpg",
    "latitude": 37.8892953,
    "longitude": 127.7716569,
    "location": {
      "province": "강원도",
      "city": "춘천",
      "town": "동면",
      "fullAddress": "강원도 춘천 동면 네이버데이터센터각"
    },
    "description": "네이버 데이터센터 각에 왔다 음식도 맛있고 공기도 좋고 풋살장도 있고 농구장도 있고 배드민턴 장도 있고 없는게 없는 것 같다. 우리 회사도 이쪽으로 이사왔으면 좋겠다 열심히 해서 우승 해야겠다"
  },
  {
    "id": 122,
    "weather": "sunny",
    "date": 1498231940,
    "imgUrl": "./images/photos/sunny122.jpg",
    "latitude": 37.8892953,
    "longitude": 127.7716569,
    "location": {
      "province": "강원도",
      "city": "춘천",
      "town": "동면",
      "fullAddress": "강원도 춘천 동면 네이버데이터센터각"
    },
    "description": "네이버 데이터센터 각에 왔다 음식도 맛있고 공기도 좋고 풋살장도 있고 농구장도 있고 배드민턴 장도 있고 없는게 없는 것 같다. 우리 회사도 이쪽으로 이사왔으면 좋겠다 열심히 해서 우승 해야겠다"
  },
  {
    "id": 123,
    "weather": "sunny",
    "date": 1498232900,
    "imgUrl": "./images/photos/sunny123.jpg",
    "latitude": 37.8892953,
    "longitude": 127.7716569,
    "location": {
      "province": "강원도",
      "city": "춘천",
      "town": "동면",
      "fullAddress": "강원도 춘천 동면 네이버데이터센터각"
    },
    "description": "네이버 데이터센터 각에 왔다 음식도 맛있고 공기도 좋고 풋살장도 있고 농구장도 있고 배드민턴 장도 있고 없는게 없는 것 같다. 우리 회사도 이쪽으로 이사왔으면 좋겠다 열심히 해서 우승 해야겠다"
  },
  {
    "id": 124,
    "weather": "sunny",
    "date": 1498233140,
    "imgUrl": "./images/photos/sunny124.jpg",
    "latitude": 37.8892953,
    "longitude": 127.7716569,
    "location": {
      "province": "강원도",
      "city": "춘천",
      "town": "동면",
      "fullAddress": "강원도 춘천 동면 네이버데이터센터각"
    },
    "description": "네이버 데이터센터 각에 왔다 음식도 맛있고 공기도 좋고 풋살장도 있고 농구장도 있고 배드민턴 장도 있고 없는게 없는 것 같다. 우리 회사도 이쪽으로 이사왔으면 좋겠다 열심히 해서 우승 해야겠다"
  },
  {
    "id": 125,
    "weather": "sunny",
    "date": 1498234210,
    "imgUrl": "./images/photos/sunny125.jpg",
    "latitude": 37.8892953,
    "longitude": 127.7716569,
    "location": {
      "province": "강원도",
      "city": "춘천",
      "town": "동면",
      "fullAddress": "강원도 춘천 동면 네이버데이터센터각"
    },
    "description": "네이버 데이터센터 각에 왔다 음식도 맛있고 공기도 좋고 풋살장도 있고 농구장도 있고 배드민턴 장도 있고 없는게 없는 것 같다. 우리 회사도 이쪽으로 이사왔으면 좋겠다 열심히 해서 우승 해야겠다"
  },
  {
    "id": 126,
    "weather": "sunny",
    "date": 1498235700,
    "imgUrl": "./images/photos/sunny126.jpg",
    "latitude": 37.8892953,
    "longitude": 127.7716569,
    "location": {
      "province": "강원도",
      "city": "춘천",
      "town": "동면",
      "fullAddress": "강원도 춘천 동면 네이버데이터센터각"
    },
    "description": "네이버 데이터센터 각에 왔다 음식도 맛있고 공기도 좋고 풋살장도 있고 농구장도 있고 배드민턴 장도 있고 없는게 없는 것 같다. 우리 회사도 이쪽으로 이사왔으면 좋겠다 열심히 해서 우승 해야겠다"
  },
  {
    "id": 127,
    "weather": "sunny",
    "date": 1498237300,
    "imgUrl": "./images/photos/sunny127.jpg",
    "latitude": 37.8892953,
    "longitude": 127.7716569,
    "location": {
      "province": "강원도",
      "city": "춘천",
      "town": "동면",
      "fullAddress": "강원도 춘천 동면 네이버데이터센터각"
    },
    "description": "네이버 데이터센터 각에 왔다 음식도 맛있고 공기도 좋고 풋살장도 있고 농구장도 있고 배드민턴 장도 있고 없는게 없는 것 같다. 우리 회사도 이쪽으로 이사왔으면 좋겠다 열심히 해서 우승 해야겠다"
  },
  {
    "id": 128,
    "weather": "sunny",
    "date": 1498239100,
    "imgUrl": "./images/photos/sunny128.jpg",
    "latitude": 37.8892953,
    "longitude": 127.7716569,
    "location": {
      " province": "강원도",
      "city": "춘천",
      "town": "동면",
      "fullAddress": "강원도 춘천 동면 네이버데이터센터각"
    },
    "description": "네이버 데이터센터 각에 왔다 음식도 맛있고 공기도 좋고 풋살장도 있고 농구장도 있고 배드민턴 장도 있고 없는게 없는 것 같다. 우리 회사도 이쪽으로 이사왔으면 좋겠다 열심히 해서 우승 해야겠다"
  },
  {
    "id": 250,
    "weather": "rainy",
    "date": 1498239100,
    "imgUrl": "./images/photos/rainy203.jpg",
    "latitude": 37.570169,
    "longitude": 126.980905,
    "location": {
      " province": "서울특별시",
      "city": "종로구",
      "town": "종로 1가",
      "fullAddress": "서울특별시 종로구 종로1가 종각역"
    },
    "description": "비오는날 집에있고싶었는데 오랜만에 밖으로 나왔다. 찝찝해도 막상 나오니까 괜찮은거같기도 하고 나온김에 여기저기 둘러보고 들어가야겠다. 종각역 근처에 막걸리집이 많은데 오랜만에 친구불러서 한잔하고 들어가야지~"
  },
  {
    "id": 251,
    "weather": "rainy",
    "date": 1498239100,
    "imgUrl": "./images/photos/rainy204.jpg",
    "latitude": 37.570169,
    "longitude": 126.980905,
    "location": {
      " province": "서울특별시",
      "city": "종로구",
      "town": "종로 1가",
      "fullAddress": "서울특별시 종로구 종로1가 종각역"
    },
    "description": "비오는날 집에있고싶었는데 오랜만에 밖으로 나왔다. 찝찝해도 막상 나오니까 괜찮은거같기도 하고 나온김에 여기저기 둘러보고 들어가야겠다. 종각역 근처에 막걸리집이 많은데 오랜만에 친구불러서 한잔하고 들어가야지~"
  },
  {
    "id": 252,
    "weather": "rainy",
    "date": 1498239100,
    "imgUrl": "./images/photos/rainy205.jpg",
    "latitude": 37.570169,
    "longitude": 126.980905,
    "location": {
      " province": "서울특별시",
      "city": "종로구",
      "town": "종로 1가",
      "fullAddress": "서울특별시 종로구 종로1가 종각역"
    },
    "description": "비오는날 집에있고싶었는데 오랜만에 밖으로 나왔다. 찝찝해도 막상 나오니까 괜찮은거같기도 하고 나온김에 여기저기 둘러보고 들어가야겠다. 종각역 근처에 막걸리집이 많은데 오랜만에 친구불러서 한잔하고 들어가야지~"
  },
  {
    "id": 253,
    "weather": "rainy",
    "date": 1498239100,
    "imgUrl": "./images/photos/rainy206.jpg",
    "latitude": 37.570169,
    "longitude": 126.980905,
    "location": {
      " province": "서울특별시",
      "city": "종로구",
      "town": "종로 1가",
      "fullAddress": "서울특별시 종로구 종로1가 종각역"
    },
    "description": "비오는날 집에있고싶었는데 오랜만에 밖으로 나왔다. 찝찝해도 막상 나오니까 괜찮은거같기도 하고 나온김에 여기저기 둘러보고 들어가야겠다. 종각역 근처에 막걸리집이 많은데 오랜만에 친구불러서 한잔하고 들어가야지~"
  },
  {
    "id": 255,
    "weather": "rainy",
    "date": 1498239100,
    "imgUrl": "./images/photos/rainy207.jpg",
    "latitude": 37.570169,
    "longitude": 126.980905,
    "location": {
      " province": "서울특별시",
      "city": "종로구",
      "town": "종로 1가",
      "fullAddress": "서울특별시 종로구 종로1가 종각역"
    },
    "description": "비오는날 집에있고싶었는데 오랜만에 밖으로 나왔다. 찝찝해도 막상 나오니까 괜찮은거같기도 하고 나온김에 여기저기 둘러보고 들어가야겠다. 종각역 근처에 막걸리집이 많은데 오랜만에 친구불러서 한잔하고 들어가야지~"
  },
  {
    "id": 256,
    "weather": "rainy",
    "date": 1498239100,
    "imgUrl": "./images/photos/rainy208.jpg",
    "latitude": 37.570169,
    "longitude": 126.980905,
    "location": {
      " province": "서울특별시",
      "city": "종로구",
      "town": "종로 1가",
      "fullAddress": "서울특별시 종로구 종로1가 종각역"
    },
    "description": "비오는날 집에있고싶었는데 오랜만에 밖으로 나왔다. 찝찝해도 막상 나오니까 괜찮은거같기도 하고 나온김에 여기저기 둘러보고 들어가야겠다. 종각역 근처에 막걸리집이 많은데 오랜만에 친구불러서 한잔하고 들어가야지~"
  },
  {
    "id": 257,
    "weather": "rainy",
    "date": 1498239100,
    "imgUrl": "./images/photos/rainy209.jpg",
    "latitude": 37.570169,
    "longitude": 126.980905,
    "location": {
      " province": "서울특별시",
      "city": "종로구",
      "town": "종로 1가",
      "fullAddress": "서울특별시 종로구 종로1가 종각역"
    },
    "description": "비오는날 집에있고싶었는데 오랜만에 밖으로 나왔다. 찝찝해도 막상 나오니까 괜찮은거같기도 하고 나온김에 여기저기 둘러보고 들어가야겠다. 종각역 근처에 막걸리집이 많은데 오랜만에 친구불러서 한잔하고 들어가야지~"
  },
  {
    "id": 258,
    "weather": "rainy",
    "date": 1498239100,
    "imgUrl": "./images/photos/rainy210.jpg",
    "latitude": 37.570169,
    "longitude": 126.980905,
    "location": {
      " province": "서울특별시",
      "city": "종로구",
      "town": "종로 1가",
      "fullAddress": "서울특별시 종로구 종로1가 종각역"
    },
    "description": "비오는날 집에있고싶었는데 오랜만에 밖으로 나왔다. 찝찝해도 막상 나오니까 괜찮은거같기도 하고 나온김에 여기저기 둘러보고 들어가야겠다. 종각역 근처에 막걸리집이 많은데 오랜만에 친구불러서 한잔하고 들어가야지~"
  },
  {
    "id": 259,
    "weather": "rainy",
    "date": 1498239100,
    "imgUrl": "./images/photos/rainy211.jpg",
    "latitude": 37.570169,
    "longitude": 126.980905,
    "location": {
      " province": "서울특별시",
      "city": "종로구",
      "town": "종로 1가",
      "fullAddress": "서울특별시 종로구 종로1가 종각역"
    },
    "description": "비오는날 집에있고싶었는데 오랜만에 밖으로 나왔다. 찝찝해도 막상 나오니까 괜찮은거같기도 하고 나온김에 여기저기 둘러보고 들어가야겠다. 종각역 근처에 막걸리집이 많은데 오랜만에 친구불러서 한잔하고 들어가야지~"
  },
  {
    "id": 260,
    "weather": "rainy",
    "date": 1498239100,
    "imgUrl": "./images/photos/rainy212.jpg",
    "latitude": 37.570169,
    "longitude": 126.980905,
    "location": {
      " province": "서울특별시",
      "city": "종로구",
      "town": "종로 1가",
      "fullAddress": "서울특별시 종로구 종로1가 종각역"
    },
    "description": "비오는날 집에있고싶었는데 오랜만에 밖으로 나왔다. 찝찝해도 막상 나오니까 괜찮은거같기도 하고 나온김에 여기저기 둘러보고 들어가야겠다. 종각역 근처에 막걸리집이 많은데 오랜만에 친구불러서 한잔하고 들어가야지~"
  },
  {
    "id": 261,
    "weather": "cloudy",
    "date": 1498239100,
    "imgUrl": "./images/photos/cloudy203.jpg",
    "latitude": 37.5482248,
    "longitude": 127.0786487,
    "location": {
      " province": "서울특별시",
      "city": "광진구",
      "town": "능동 능동로216",
      "fullAddress": "서울특별시 광진구 능동 능동로216 어린이대공원"
    },
    "description": "구름낀날이라 그런지 사진이 이쁘게 안찍힌다ㅠㅠ 여기저기 돌아다니면서 많이찍긴했는데 별로 만족이안되네~ 다음에 맑은날 더 많이 찍어야지. 그래도 날씨가 흐린거 치고는 괜찮은게 몇개 있는거 같기도 ~"
  },
  {
    "id": 262,
    "weather": "cloudy",
    "date": 1498239100,
    "imgUrl": "./images/photos/cloudy204.jpg",
    "latitude": 37.5482248,
    "longitude": 127.0786487,
    "location": {
      " province": "서울특별시",
      "city": "광진구",
      "town": "능동 능동로216",
      "fullAddress": "서울특별시 광진구 능동 능동로216 어린이대공원"
    },
    "description": "구름낀날이라 그런지 사진이 이쁘게 안찍힌다ㅠㅠ 여기저기 돌아다니면서 많이찍긴했는데 별로 만족이안되네~ 다음에 맑은날 더 많이 찍어야지. 그래도 날씨가 흐린거 치고는 괜찮은게 몇개 있는거 같기도 ~"
  },
  {
    "id": 263,
    "weather": "cloudy",
    "date": 1498239100,
    "imgUrl": "./images/photos/cloudy205.jpg",
    "latitude": 37.5482248,
    "longitude": 127.0786487,
    "location": {
      " province": "서울특별시",
      "city": "광진구",
      "town": "능동 능동로216",
      "fullAddress": "서울특별시 광진구 능동 능동로216 어린이대공원"
    },
    "description": "구름낀날이라 그런지 사진이 이쁘게 안찍힌다ㅠㅠ 여기저기 돌아다니면서 많이찍긴했는데 별로 만족이안되네~ 다음에 맑은날 더 많이 찍어야지. 그래도 날씨가 흐린거 치고는 괜찮은게 몇개 있는거 같기도 ~"
  },
  {
    "id": 264,
    "weather": "cloudy",
    "date": 1498239100,
    "imgUrl": "./images/photos/cloudy206.jpg",
    "latitude": 37.5482248,
    "longitude": 127.0786487,
    "location": {
      " province": "서울특별시",
      "city": "광진구",
      "town": "능동 능동로216",
      "fullAddress": "서울특별시 광진구 능동 능동로216 어린이대공원"
    },
    "description": "구름낀날이라 그런지 사진이 이쁘게 안찍힌다ㅠㅠ 여기저기 돌아다니면서 많이찍긴했는데 별로 만족이안되네~ 다음에 맑은날 더 많이 찍어야지. 그래도 날씨가 흐린거 치고는 괜찮은게 몇개 있는거 같기도 ~"
  },
  {
    "id": 265,
    "weather": "cloudy",
    "date": 1498239100,
    "imgUrl": "./images/photos/cloudy207.jpg",
    "latitude": 37.5482248,
    "longitude": 127.0786487,
    "location": {
      " province": "서울특별시",
      "city": "광진구",
      "town": "능동 능동로216",
      "fullAddress": "서울특별시 광진구 능동 능동로216 어린이대공원"
    },
    "description": "구름낀날이라 그런지 사진이 이쁘게 안찍힌다ㅠㅠ 여기저기 돌아다니면서 많이찍긴했는데 별로 만족이안되네~ 다음에 맑은날 더 많이 찍어야지. 그래도 날씨가 흐린거 치고는 괜찮은게 몇개 있는거 같기도 ~"
  },
  {
    "id": 266,
    "weather": "cloudy",
    "date": 1498239100,
    "imgUrl": "./images/photos/cloudy208.jpg",
    "latitude": 37.5482248,
    "longitude": 127.0786487,
    "location": {
      " province": "서울특별시",
      "city": "광진구",
      "town": "능동 능동로216",
      "fullAddress": "서울특별시 광진구 능동 능동로216 어린이대공원"
    },
    "description": "구름낀날이라 그런지 사진이 이쁘게 안찍힌다ㅠㅠ 여기저기 돌아다니면서 많이찍긴했는데 별로 만족이안되네~ 다음에 맑은날 더 많이 찍어야지. 그래도 날씨가 흐린거 치고는 괜찮은게 몇개 있는거 같기도 ~"
  },
  {
    "id": 267,
    "weather": "cloudy",
    "date": 1498239100,
    "imgUrl": "./images/photos/cloudy209.jpg",
    "latitude": 37.5482248,
    "longitude": 127.0786487,
    "location": {
      " province": "서울특별시",
      "city": "광진구",
      "town": "능동 능동로216",
      "fullAddress": "서울특별시 광진구 능동 능동로216 어린이대공원"
    },
    "description": "구름낀날이라 그런지 사진이 이쁘게 안찍힌다ㅠㅠ 여기저기 돌아다니면서 많이찍긴했는데 별로 만족이안되네~ 다음에 맑은날 더 많이 찍어야지. 그래도 날씨가 흐린거 치고는 괜찮은게 몇개 있는거 같기도 ~"
  },
  {
    "id": 268,
    "weather": "cloudy",
    "date": 1498239100,
    "imgUrl": "./images/photos/cloudy210.jpg",
    "latitude": 37.5482248,
    "longitude": 127.0786487,
    "location": {
      " province": "서울특별시",
      "city": "광진구",
      "town": "능동 능동로216",
      "fullAddress": "서울특별시 광진구 능동 능동로216 어린이대공원"
    },
    "description": "구름낀날이라 그런지 사진이 이쁘게 안찍힌다ㅠㅠ 여기저기 돌아다니면서 많이찍긴했는데 별로 만족이안되네~ 다음에 맑은날 더 많이 찍어야지. 그래도 날씨가 흐린거 치고는 괜찮은게 몇개 있는거 같기도 ~"
  },
  {
    "id": 269,
    "weather": "cloudy",
    "date": 1498239100,
    "imgUrl": "./images/photos/cloudy211.jpg",
    "latitude": 37.5482248,
    "longitude": 127.0786487,
    "location": {
      " province": "서울특별시",
      "city": "광진구",
      "town": "능동 능동로216",
      "fullAddress": "서울특별시 광진구 능동 능동로216 어린이대공원"
    },
    "description": "구름낀날이라 그런지 사진이 이쁘게 안찍힌다ㅠㅠ 여기저기 돌아다니면서 많이찍긴했는데 별로 만족이안되네~ 다음에 맑은날 더 많이 찍어야지. 그래도 날씨가 흐린거 치고는 괜찮은게 몇개 있는거 같기도 ~"
  },
  {
    "id": 270,
    "weather": "cloudy",
    "date": 1498239100,
    "imgUrl": "./images/photos/cloudy212.jpg",
    "latitude": 37.5482248,
    "longitude": 127.0786487,
    "location": {
      " province": "서울특별시",
      "city": "광진구",
      "town": "능동 능동로216",
      "fullAddress": "서울특별시 광진구 능동 능동로216 어린이대공원"
    },
    "description": "구름낀날이라 그런지 사진이 이쁘게 안찍힌다ㅠㅠ 여기저기 돌아다니면서 많이찍긴했는데 별로 만족이안되네~ 다음에 맑은날 더 많이 찍어야지. 그래도 날씨가 흐린거 치고는 괜찮은게 몇개 있는거 같기도 ~"
  },
  {
    "id": 300,
    "weather": "snowy",
    "date": 1498239100,
    "imgUrl": "./images/photos/snowy1.jpg",
    "latitude": 37.2063632,
    "longitude": 128.8353614,
    "location": {
      " province": "강원도",
      "city": "정선군",
      "town": "고한읍",
      "fullAddress": "강원도 정선군 고한읍 하이원길 424"
    },
    "description": "눈 내린날 놀러가서 찍은사진~ 오랜만에 스키장에서 여유있게 놀면서 찍은 사진들. 개장한지 얼마 안되서 그런지 사람이 별로없어서 야간까지 뽕뽑고왔다 ㅋㅋ 매년 시즌권 끊어서 놀아야지~ 폐장전에 한번더 가야겠다."
  },
  {
    "id": 301,
    "weather": "snowy",
    "date": 1498239100,
    "imgUrl": "./images/photos/snowy2.jpg",
    "latitude": 37.2063632,
    "longitude": 128.8353614,
    "location": {
      " province": "강원도",
      "city": "정선군",
      "town": "고한읍",
      "fullAddress": "강원도 정선군 고한읍 하이원길 424"
    },
    "description": "눈 내린날 놀러가서 찍은사진~ 오랜만에 스키장에서 여유있게 놀면서 찍은 사진들. 개장한지 얼마 안되서 그런지 사람이 별로없어서 야간까지 뽕뽑고왔다 ㅋㅋ "
  },
  {
    "id": 302,
    "weather": "snowy",
    "date": 1498239100,
    "imgUrl": "./images/photos/snowy3.jpg",
    "latitude": 37.2063632,
    "longitude": 128.8353614,
    "location": {
      " province": "강원도",
      "city": "정선군",
      "town": "고한읍",
      "fullAddress": "강원도 정선군 고한읍 하이원길 424"
    },
    "description": "눈 내린날 놀러가서 찍은사진~ 오랜만에 스키장에서 여유있게 놀면서 찍은 사진들. 개장한지 얼마 안되서 그런지 사람이 별로없어서 야간까지 뽕뽑고왔다 ㅋㅋ "
  },
  {
    "id": 303,
    "weather": "snowy",
    "date": 1498239100,
    "imgUrl": "./images/photos/snowy4.jpg",
    "latitude": 37.2063632,
    "longitude": 128.8353614,
    "location": {
      " province": "강원도",
      "city": "정선군",
      "town": "고한읍",
      "fullAddress": "강원도 정선군 고한읍 하이원길 424"
    },
    "description": "눈 내린날 놀러가서 찍은사진~ 오랜만에 스키장에서 여유있게 놀면서 찍은 사진들. 개장한지 얼마 안되서 그런지 사람이 별로없어서 야간까지 뽕뽑고왔다 ㅋㅋ "
  },
  {
    "id": 304,
    "weather": "snowy",
    "date": 1498239100,
    "imgUrl": "./images/photos/snowy5.jpg",
    "latitude": 37.2063632,
    "longitude": 128.8353614,
    "location": {
      " province": "강원도",
      "city": "정선군",
      "town": "고한읍",
      "fullAddress": "강원도 정선군 고한읍 하이원길 424"
    },
    "description": "눈 내린날 놀러가서 찍은사진~ 오랜만에 스키장에서 여유있게 놀면서 찍은 사진들. 개장한지 얼마 안되서 그런지 사람이 별로없어서 야간까지 뽕뽑고왔다 ㅋㅋ "
  },
  {
    "id": 305,
    "weather": "snowy",
    "date": 1498239100,
    "imgUrl": "./images/photos/snowy6.jpg",
    "latitude": 37.2063632,
    "longitude": 128.8353614,
    "location": {
      " province": "강원도",
      "city": "정선군",
      "town": "고한읍",
      "fullAddress": "강원도 정선군 고한읍 하이원길 424"
    },
    "description": "눈 내린날 놀러가서 찍은사진~ 오랜만에 스키장에서 여유있게 놀면서 찍은 사진들. 개장한지 얼마 안되서 그런지 사람이 별로없어서 야간까지 뽕뽑고왔다 ㅋㅋ "
  },
  {
    "id": 306,
    "weather": "snowy",
    "date": 1498239100,
    "imgUrl": "./images/photos/snowy7.jpg",
    "latitude": 37.2063632,
    "longitude": 128.8353614,
    "location": {
      " province": "강원도",
      "city": "정선군",
      "town": "고한읍",
      "fullAddress": "강원도 정선군 고한읍 하이원길 424"
    },
    "description": "눈 내린날 놀러가서 찍은사진~ 오랜만에 스키장에서 여유있게 놀면서 찍은 사진들. 개장한지 얼마 안되서 그런지 사람이 별로없어서 야간까지 뽕뽑고왔다 ㅋㅋ "
  },
  {
    "id": 307,
    "weather": "snowy",
    "date": 1498239100,
    "imgUrl": "./images/photos/snowy8.jpg",
    "latitude": 37.2063632,
    "longitude": 128.8353614,
    "location": {
      " province": "강원도",
      "city": "정선군",
      "town": "고한읍",
      "fullAddress": "강원도 정선군 고한읍 하이원길 424"
    },
    "description": "눈 내린날 놀러가서 찍은사진~ 오랜만에 스키장에서 여유있게 놀면서 찍은 사진들. 개장한지 얼마 안되서 그런지 사람이 별로없어서 야간까지 뽕뽑고왔다 ㅋㅋ "
  },
  {
    "id": 308,
    "weather": "snowy",
    "date": 1498239100,
    "imgUrl": "./images/photos/snowy9.jpg",
    "latitude": 37.2063632,
    "longitude": 128.8353614,
    "location": {
      " province": "강원도",
      "city": "정선군",
      "town": "고한읍",
      "fullAddress": "강원도 정선군 고한읍 하이원길 424"
    },
    "description": "눈 내린날 놀러가서 찍은사진~ 오랜만에 스키장에서 여유있게 놀면서 찍은 사진들. 개장한지 얼마 안되서 그런지 사람이 별로없어서 야간까지 뽕뽑고왔다 ㅋㅋ "
  },
  {
    "id": 309,
    "weather": "snowy",
    "date": 1498239100,
    "imgUrl": "./images/photos/snowy10.jpg",
    "latitude": 37.2063632,
    "longitude": 128.8353614,
    "location": {
      " province": "강원도",
      "city": "정선군",
      "town": "고한읍",
      "fullAddress": "강원도 정선군 고한읍 하이원길 424"
    },
    "description": "눈 내린날 놀러가서 찍은사진~ 오랜만에 스키장에서 여유있게 놀면서 찍은 사진들. 개장한지 얼마 안되서 그런지 사람이 별로없어서 야간까지 뽕뽑고왔다 ㅋㅋ "
  },
  {
    "id": 403,
    "weather": "sunny",
    "date": 1498230000,
    "imgUrl": "./images/photos/sunny403.jpg",
    "latitude": 37.8892953,
    "longitude": 127.7716569,
    "location": {
      "province": "강원도",
      "city": "춘천",
      "town": "동면",
      "fullAddress": "강원도 춘천 동면 네이버데이터센터각"
    },
    "description": "네이버 데이터센터 각에 왔다 음식도 맛있고 공기도 좋고 풋살장도 있고 농구장도 있고 배드민턴 장도 있고 없는게 없는 것 같다. 우리 회사도 이쪽으로 이사왔으면 좋겠다 열심히 해서 우승 해야겠다"
  },
  {
    "id": 404,
    "weather": "sunny",
    "date": 1498230000,
    "imgUrl": "./images/photos/sunny404.jpg",
    "latitude": 37.8892953,
    "longitude": 127.7716569,
    "location": {
      "province": "강원도",
      "city": "춘천",
      "town": "동면",
      "fullAddress": "강원도 춘천 동면 네이버데이터센터각"
    },
    "description": "네이버 데이터센터 각에 왔다 음식도 맛있고 공기도 좋고 풋살장도 있고 농구장도 있고 배드민턴 장도 있고 없는게 없는 것 같다. 우리 회사도 이쪽으로 이사왔으면 좋겠다 열심히 해서 우승 해야겠다"
  },
  {
    "id": 405,
    "weather": "cloudy",
    "date": 1498230000,
    "imgUrl": "./images/photos/cloudy400.jpg",
    "latitude": 37.8892953,
    "longitude": 127.7716569,
    "location": {
      "province": "강원도",
      "city": "춘천",
      "town": "동면",
      "fullAddress": "강원도 춘천 동면 네이버데이터센터각"
    },
    "description": "네이버 데이터센터 각에 왔다 음식도 맛있고 공기도 좋고 풋살장도 있고 농구장도 있고 배드민턴 장도 있고 없는게 없는 것 같다. 우리 회사도 이쪽으로 이사왔으면 좋겠다 열심히 해서 우승 해야겠다"
  },
  {
    "id": 406,
    "weather": "cloudy",
    "date": 1498230000,
    "imgUrl": "./images/photos/cloudy401.jpg",
    "latitude": 37.8892953,
    "longitude": 127.7716569,
    "location": {
      "province": "강원도",
      "city": "춘천",
      "town": "동면",
      "fullAddress": "강원도 춘천 동면 네이버데이터센터각"
    },
    "description": "네이버 데이터센터 각에 왔다 음식도 맛있고 공기도 좋고 풋살장도 있고 농구장도 있고 배드민턴 장도 있고 없는게 없는 것 같다. 우리 회사도 이쪽으로 이사왔으면 좋겠다 열심히 해서 우승 해야겠다"
  },
  {
    "id": 500,
    "weather": "rainy",
    "date": 1489319121,
    "imgUrl": "./images/photos/rainy500.jpg",
    "latitude": 35.1586975,
    "longitude": 129.1581955,
    "location": {
      "province": "부산광역시",
      "city": "해운대구",
      "town": "중동",
      "fullAddress": "부산광역시 해운대구 중동 해운대해수욕장"
    },
    "description": "오 ㅋㅋ 부산해운대 도착하니까 비 그침 오랜만에 부산와서 친구들 만나고 여유있게 해운대 갔다가 동네로~ 사진도 많이찍고 동네친구들 10년만에 만난거같다. 자주와야지ㅠㅠ"
  },
  {
    "id": 501,
    "weather": "rainy",
    "date": 1489319121,
    "imgUrl": "./images/photos/rainy501.jpg",
    "latitude": 35.1586975,
    "longitude": 129.1581955,
    "location": {
      "province": "부산광역시",
      "city": "해운대구",
      "town": "중동",
      "fullAddress": "부산광역시 해운대구 중동 해운대해수욕장"
    },
    "description": "오 ㅋㅋ 부산해운대 도착하니까 비 그침 오랜만에 부산와서 친구들 만나고 여유있게 해운대 갔다가 동네로~ 사진도 많이찍고 동네친구들 10년만에 만난거같다. 자주와야지ㅠㅠ"
  },
  {
    "id": 502,
    "weather": "rainy",
    "date": 1489319121,
    "imgUrl": "./images/photos/rainy502.jpg",
    "latitude": 35.1586975,
    "longitude": 129.1581955,
    "location": {
      "province": "부산광역시",
      "city": "해운대구",
      "town": "중동",
      "fullAddress": "부산광역시 해운대구 중동 해운대해수욕장"
    },
    "description": "오 ㅋㅋ 부산해운대 도착하니까 비 그침 오랜만에 부산와서 친구들 만나고 여유있게 해운대 갔다가 동네로~ 사진도 많이찍고 동네친구들 10년만에 만난거같다. 자주와야지ㅠㅠ"
  },
  {
    "id": 504,
    "weather": "rainy",
    "date": 1489319121,
    "imgUrl": "./images/photos/rainy504.jpg",
    "latitude": 35.1586975,
    "longitude": 129.1581955,
    "location": {
      "province": "부산광역시",
      "city": "해운대구",
      "town": "중동",
      "fullAddress": "부산광역시 해운대구 중동 해운대해수욕장"
    },
    "description": "오 ㅋㅋ 부산해운대 도착하니까 비 그침 오랜만에 부산와서 친구들 만나고 여유있게 해운대 갔다가 동네로~ 사진도 많이찍고 동네친구들 10년만에 만난거같다. 자주와야지ㅠㅠ"
  },
  {
    "id": 505,
    "weather": "rainy",
    "date": 1489319121,
    "imgUrl": "./images/photos/rainy505.jpg",
    "latitude": 35.1586975,
    "longitude": 129.1581955,
    "location": {
      "province": "부산광역시",
      "city": "해운대구",
      "town": "중동",
      "fullAddress": "부산광역시 해운대구 중동 해운대해수욕장"
    },
    "description": "오 ㅋㅋ 부산해운대 도착하니까 비 그침 오랜만에 부산와서 친구들 만나고 여유있게 해운대 갔다가 동네로~ 사진도 많이찍고 동네친구들 10년만에 만난거같다. 자주와야지ㅠㅠ"
  },
  {
    "id": 600,
    "weather": "cloudy",
    "date": 1498239100,
    "imgUrl": "./images/photos/cloudy600.png",
    "latitude": 37.5482248,
    "longitude": 127.0786487,
    "location": {
      " province": "서울특별시",
      "city": "광진구",
      "town": "능동 능동로216",
      "fullAddress": "서울특별시 광진구 능동 능동로216 어린이대공원"
    },
    "description": "구름낀날이라 그런지 사진이 이쁘게 안찍힌다ㅠㅠ 여기저기 돌아다니면서 많이찍긴했는데 별로 만족이안되네~ 다음에 맑은날 더 많이 찍어야지. 그래도 날씨가 흐린거 치고는 괜찮은게 몇개 있는거 같기도 ~"
  }
]
